<?xml version="1.0" encoding="UTF-8"?>
<beans xmlns="http://www.springframework.org/schema/beans"
       xmlns:xsi="http://www.w3.org/2001/XMLSchema-instance"
       xmlns:p="http://www.springframework.org/schema/p"
       xmlns:tx="http://www.springframework.org/schema/tx"
       xsi:schemaLocation="
          http://www.springframework.org/schema/beans http://www.springframework.org/schema/beans/spring-beans.xsd
          http://www.springframework.org/schema/tx http://www.springframework.org/schema/tx/spring-tx.xsd">

    <tx:annotation-driven/>

    <!-- Datasource -->
    <bean id="dataSource" class="org.springframework.jdbc.datasource.DriverManagerDataSource">
        <property name="driverClassName" value="com.mysql.cj.jdbc.Driver"/>
        <property name="url" value="jdbc:mysql://localhost:3306/spring_hibernate"/>
        <property name="username" value="root"/>
        <property name="password" value="Sujan@123"/>
    </bean>

    <!-- Hibernate SessionFactory -->
    <bean id="sessionFactory" class="org.springframework.orm.hibernate5.LocalSessionFactoryBean">
        <property name="dataSource" ref="dataSource"/>
        <property name="hibernateProperties">
            <props>
                <prop key="hibernate.dialect">org.hibernate.dialect.MySQL57Dialect</prop>
                <prop key="hibernate.show_sql">true</prop>
                <prop key="hibernate.hbm2ddl.auto">update</prop>
            </props>
        </property>
        <property name="annotatedClasses">
            <list>
                <value>org.example.Student</value>
            </list>
        </property>
    </bean>

    <!-- Hibernate Template -->
    <bean id="hibernateTemplate" class="org.springframework.orm.hibernate5.HibernateTemplate">
        <property name="sessionFactory" ref="sessionFactory"/>
    </bean>

    <!-- Transaction Manager -->
    <bean id="transactionManager" class="org.springframework.orm.hibernate5.HibernateTransactionManager">
        <property name="sessionFactory" ref="sessionFactory"/>
    </bean>

    <!-- StudentDao -->
    <bean id="studentDao" class="org.example.StudentDao">
        <property name="hibernateTemplate" ref="hibernateTemplate"/>
    </bean>

</beans>
